pymcdm/__init__.py
pymcdm/correlations.py
pymcdm/distances.py
pymcdm/helpers.py
pymcdm/normalizations.py
pymcdm/validators.py
pymcdm/io/__init__.py
pymcdm/io/mcda_problem.py
pymcdm/io/mcda_results.py
pymcdm/io/table.py
pymcdm/io/tabledesc.py
pymcdm/methods/__init__.py
pymcdm/methods/aras.py
pymcdm/methods/aroman.py
pymcdm/methods/balanced_spotis.py
pymcdm/methods/cocoso.py
pymcdm/methods/codas.py
pymcdm/methods/comet.py
pymcdm/methods/copras.py
pymcdm/methods/edas.py
pymcdm/methods/ervd.py
pymcdm/methods/lmaw.py
pymcdm/methods/lopm.py
pymcdm/methods/mabac.py
pymcdm/methods/mairca.py
pymcdm/methods/marcos.py
pymcdm/methods/mcda_method.py
pymcdm/methods/moora.py
pymcdm/methods/ocra.py
pymcdm/methods/probid.py
pymcdm/methods/promethee_ii.py
pymcdm/methods/rafsi.py
pymcdm/methods/ram.py
pymcdm/methods/rim.py
pymcdm/methods/spotis.py
pymcdm/methods/sprobid.py
pymcdm/methods/topsis.py
pymcdm/methods/vikor.py
pymcdm/methods/waspas.py
pymcdm/methods/wpm.py
pymcdm/methods/wsm.py
pymcdm/methods/comet_tools/__init__.py
pymcdm/methods/comet_tools/compromise_expert.py
pymcdm/methods/comet_tools/esp_expert.py
pymcdm/methods/comet_tools/function_expert.py
pymcdm/methods/comet_tools/local_weights.py
pymcdm/methods/comet_tools/manual_expert.py
pymcdm/methods/comet_tools/method_expert.py
pymcdm/methods/comet_tools/structural_comet.py
pymcdm/methods/comet_tools/triad_supported_expert.py
pymcdm/methods/comet_tools/triads_consistency.py
pymcdm/methods/partial/__init__.py
pymcdm/methods/partial/promethee_i.py
pymcdm/visuals/__init__.py
pymcdm/visuals/boxplot.py
pymcdm/visuals/comet_2d_esp_plot.py
pymcdm/visuals/comet_2d_plot.py
pymcdm/visuals/comet_3d_esp_plot.py
pymcdm/visuals/comet_3d_plot.py
pymcdm/visuals/comet_contourf.py
pymcdm/visuals/comet_tfns.py
pymcdm/visuals/correlation_heatmap.py
pymcdm/visuals/correlation_plot.py
pymcdm/visuals/mej_plot.py
pymcdm/visuals/polar_plot.py
pymcdm/visuals/polar_weights.py
pymcdm/visuals/promethee_I_flows.py
pymcdm/visuals/promethee_I_graph.py
pymcdm-1.4.0.dist-info/licenses/LICENSE
pymcdm-1.4.0.dist-info/METADATA
pymcdm-1.4.0.dist-info/WHEEL
pymcdm-1.4.0.dist-info/top_level.txt
pymcdm-1.4.0.dist-info/RECORD
