Metadata-Version: 2.4
Name: pymcdm
Version: 1.4.0
Summary: Python library for Multi-Criteria Decision-Making
Author-email: Andrii Shekhovtsov <andrii-shekhovtsov@zut.edu.pl>, Bartłomiej Kizielewicz <bartlomiej-kizielewicz@zut.edu.pl>
License-Expression: MIT
Project-URL: Homepage, https://github.com/kotbaton/pymcdm
Project-URL: Issues, https://github.com/kotbaton/pymcdm/issues
Project-URL: Documentation, https://pymcdm.readthedocs.io/
Project-URL: Changelog, https://github.com/kotbaton/pymcdm/blob/master/CHANGELOG.md
Keywords: MCDM,Multi-Criteria Decision-Making,Decision Analysis,Operations Research
Classifier: Programming Language :: Python :: 3
Classifier: Operating System :: OS Independent
Requires-Python: >=3.11
License-File: LICENSE
Requires-Dist: numpy
Requires-Dist: scipy
Requires-Dist: pandas
Requires-Dist: matplotlib
Requires-Dist: tabulate
Provides-Extra: docs
Requires-Dist: sphinx-autoapi; extra == "docs"
Requires-Dist: nbsphinx; extra == "docs"
Requires-Dist: IPython; extra == "docs"
Requires-Dist: myst_parser; extra == "docs"
Requires-Dist: sphinx-rtd-theme; extra == "docs"
Requires-Dist: recommonmark; extra == "docs"
Requires-Dist: pandoc; extra == "docs"
Dynamic: license-file
